{"_path":"/modules/licensing/further_reading","_dir":"licensing","_draft":false,"_partial":false,"_locale":"","title":"Further Reading","description":"","type":"reading","order":6,"body":{"type":"root","children":[{"type":"element","tag":"h3","props":{"id":"further-reading"},"children":[{"type":"text","value":"Further Reading"}]}],"toc":{"title":"","searchDepth":2,"depth":2,"links":[{"id":"further-reading","depth":3,"text":"Further Reading"}]}},"_type":"markdown","_id":"local_fs:modules:licensing:further_reading.md","_source":"local_fs","_file":"modules/licensing/further_reading.md","_stem":"modules/licensing/further_reading","_extension":"md","plainText":"---\ntitle: Further Reading \ntype: reading\norder: 6\n---\n\n### Further Reading\n"}